test_looper/__init__.py
test_looper/client/MultiMachineTestRunner.py
test_looper/client/PerformanceTestReporter.py
test_looper/client/TestScriptRunner.py
test_looper/client/__init__.py
test_looper/client/_version.py
test_looper/client/build.py
test_looper/client/docker.py
test_looper/client/env.py
test_looper-0.1.dist-info/DESCRIPTION.rst
test_looper-0.1.dist-info/METADATA
test_looper-0.1.dist-info/RECORD
test_looper-0.1.dist-info/WHEEL
test_looper-0.1.dist-info/metadata.json
test_looper-0.1.dist-info/top_level.txt
