Metadata-Version: 2.0
Name: test-looper
Version: 0.1
Summary: Helper package for the test-looper statistical testing service
Home-page: http://www.ufora.com/
Author: Ufora Inc.
Author-email: info@ufora.com
License: Apache
Keywords: CI Continuous Integration cloud ec2 testing QA
Platform: UNKNOWN
Classifier: Development Status :: 3 - Alpha
Classifier: Environment :: Console
Classifier: Intended Audience :: Developers
Classifier: License :: OSI Approved :: Apache Software License
Classifier: Operating System :: OS Independent
Classifier: Programming Language :: Python :: 2.7
Classifier: Topic :: Software Development :: Testing
